llm_meter/__init__.py
llm_meter/budget.py
llm_meter/budget_middleware.py
llm_meter/context.py
llm_meter/core.py
llm_meter/middleware.py
llm_meter/models.py
llm_meter/cli/__init__.py
llm_meter/cli/exporters.py
llm_meter/cli/main.py
llm_meter/cli/models.py
llm_meter/providers/__init__.py
llm_meter/providers/anthropic.py
llm_meter/providers/base.py
llm_meter/providers/openai.py
llm_meter/providers/pricing.py
llm_meter/storage/__init__.py
llm_meter/storage/base.py
llm_meter/storage/batcher.py
llm_meter/storage/manager.py
llm_meter/storage/postgres.py
llm_meter-0.3.4.dist-info/METADATA
llm_meter-0.3.4.dist-info/WHEEL
llm_meter-0.3.4.dist-info/entry_points.txt
llm_meter-0.3.4.dist-info/licenses/LICENSE
llm_meter-0.3.4.dist-info/RECORD
