Metadata-Version: 2.4
Name: llm-meter
Version: 0.3.4
Summary: Accurate LLM usage & cost tracking for Python backends (FastAPI-native)
Project-URL: Homepage, https://github.com/doubledare704/llm-meter
Project-URL: Issues, https://github.com/doubledare704/llm-meter/issues
Author-email: Oleksii Ovdiienko <doubledare704@gmail.com>
License: MIT
License-File: LICENSE
Keywords: cost-tracking,fastapi,instrumentation,llm,middleware,openai,usage
Classifier: Development Status :: 4 - Beta
Classifier: Framework :: FastAPI
Classifier: Intended Audience :: Developers
Classifier: License :: OSI Approved :: MIT License
Classifier: Programming Language :: Python :: 3
Classifier: Programming Language :: Python :: 3.10
Classifier: Programming Language :: Python :: 3.11
Classifier: Programming Language :: Python :: 3.12
Classifier: Topic :: Software Development :: Libraries :: Python Modules
Requires-Python: >=3.10
Requires-Dist: aiosqlite>=0.22.1
Requires-Dist: fastapi>=0.128.0
Requires-Dist: openai>=2.14.0
Requires-Dist: pydantic>=2.12.5
Requires-Dist: rich>=13.0.0
Requires-Dist: sqlalchemy[asyncio]>=2.0.45
Requires-Dist: typer>=0.21.0
Provides-Extra: excel
Requires-Dist: openpyxl>=3.1.5; extra == 'excel'
Provides-Extra: postgres
Requires-Dist: asyncpg>=0.29.0; extra == 'postgres'
Provides-Extra: streaming
Requires-Dist: tiktoken>=0.12.0; extra == 'streaming'
